mp3chaps2/__init__.py
mp3chaps2/mp3chaps.py
mp3chaps2-1.0.5.dist-info/METADATA
mp3chaps2-1.0.5.dist-info/WHEEL
mp3chaps2-1.0.5.dist-info/entry_points.txt
mp3chaps2-1.0.5.dist-info/licenses/LICENSE.txt
mp3chaps2-1.0.5.dist-info/RECORD
