Metadata-Version: 2.4
Name: mp3chaps2
Version: 1.0.5
Summary: A tool for managing MP3 chapter markers, modified from mp3chaps. The original version can be found here: https://github.com/dskrad/mp3chaps
Author-email: Steven Zuber <stevenjzuber@gmail.com>
License-Expression: MIT
License-File: LICENSE.txt
Keywords: audio,chapters,metadata,mp3,podcast
Classifier: Development Status :: 5 - Production/Stable
Classifier: Environment :: Console
Classifier: Intended Audience :: End Users/Desktop
Classifier: License :: OSI Approved :: MIT License
Classifier: Operating System :: OS Independent
Classifier: Programming Language :: Python :: 3
Classifier: Programming Language :: Python :: 3.7
Classifier: Programming Language :: Python :: 3.8
Classifier: Programming Language :: Python :: 3.9
Classifier: Programming Language :: Python :: 3.10
Classifier: Programming Language :: Python :: 3.11
Classifier: Topic :: Multimedia :: Sound/Audio
Classifier: Topic :: Utilities
Requires-Python: >=3.7
Requires-Dist: docopt>=0.6.2
Requires-Dist: eyed3>=0.9.7
Provides-Extra: dev
Requires-Dist: build>=1.2.2.post1; extra == 'dev'
Requires-Dist: pytest>=7.4.4; extra == 'dev'
Requires-Dist: twine>=6.1.0; extra == 'dev'
